FPA_CALC.v
/*This Part of code represents the floating point CALC state and is designed to fetch two 
iEE754 format inputs from Floating Point input 1 and Input 2 state and to perform the 
addition on them by first separating the inputs into sign, exponent and mantissa. It also performs
normalization and checks the underflow and overflow condition.
*/
module fpa_adder(input clk_34,rst_34,
input [15:0]Finput1_34,Finput2_34,
output reg[15:0]FPSUM_34,
output reg Ovf_Flag_34,Unf_Flag_34);

reg [12:0] M1_ST0,M2_ST0,M1_ST1,M2_ST1,M_Final;  //Mantissa Registers of input 1 & 2 
reg [4:0]E1_ST0,E2_ST0,E1_ST1,E2_ST1,E_Final;  //Exponent Registers of input 1 & 2
reg S1_ST0,S2_ST0,S1_ST1,S2_ST1,S_Final;      //Sign bit register of input 1 & 2
reg Bit_Ovf;    //For storing the values for bit overflow condition
reg [14:0] M1_Add,M2_Add,M_Sum,Fsum; //Register for addition
reg [12:0] M1_ST0_temp,M2_ST0_temp;
reg [4:0] E1_ST0_temp, E2_ST0_temp,Temp;

always @(*) begin
 //Separate the input 1 into sign, exponent & mantissa
  S1_ST0 = Finput1_34[15] ;                //Sign bit of input 1
  E1_ST0 = Finput1_34[14:10];              //Exponent bit of input 1
  M1_ST0[11:0] = {Finput1_34[9:0],2'b00};  //Mantissa of input 1 with guard and round bit

 //Separate the input 2 into sign, exponent and mantissa
  S2_ST0 = Finput2_34[15];                 //Sign bit of input2
  E2_ST0 = Finput2_34[14:10];              //Exponent bit of input 2
  M2_ST0[11:0] = {Finput2_34[9:0],2'b00};  //Mantissa of input 2 with guard and round bit 

//Add the prefix bit to both matissa for making 1.XX format
if (Finput1_34 == 0) begin
M1_ST0[12] = 1'b0 ;
end
else begin
M1_ST0[12] = 1'b1 ;
end
if (Finput2_34 == 0) begin
M2_ST0[12] = 1'b0 ;
end
else begin
M2_ST0[12] = 1'b1 ;
end
//Compare the exponents of both inputs

if (E1_ST0 < E2_ST0) begin 
  Temp =  E2_ST0-E1_ST0;//Compare exponent 2 > exponent 1         
  M1_ST1 = M1_ST0>>Temp; 
  M2_ST1 = M2_ST0; //Shift the bits to right by 1 of input1's mantissa
  E1_ST1 = E2_ST0;//Increment the input 1's exponent by 1
end
else begin //compare exponent 1 > exponent 2
  Temp =  E1_ST0-E2_ST0;
  M1_ST1 = M1_ST0;
  M2_ST1 = M2_ST0>>Temp;//Shift the bits to right by 1 of input2's mantissa
  E1_ST1 = E1_ST0;//Increment the input2's exponent by 1
end
  
  S1_ST1 = S1_ST0;      
  S2_ST1 = S2_ST0;

//Adder Stage 
//Mantissa is prefixed by two bit so as not to lose sign bit in case of overflow addition
//Two's complement for the negative number 
M1_Add = (S1_ST1== 1'b1) ? (~{2'b00, M1_ST1}) + 1 : {2'b00, M1_ST1} ;
M2_Add = (S2_ST1 == 1'b1) ? (~{2'b00, M2_ST1}) + 1 : {2'b00, M2_ST1} ; 
M_Sum = M1_Add + M2_Add ;//Addition of Final Mantissa
//If result is negative then perform 2's complement
Fsum = ((M_Sum[14]) == 1'b0) ? M_Sum : ~M_Sum + 1 ;

//Performing normalization & checking the overflow and underflow condition and gives the final output
S_Final = M_Sum[14];  //Fetching the sign bit of final result
//Check the bit overflow condition so that no one will be left in the 
//1st & 3rd bit while transfering into 13 bit mantissa
Bit_Ovf = Fsum[14] ^ Fsum[13] ;    
//If bit overflow is present then shifts the bits of final result to right 
M_Final = (Bit_Ovf==1'b1)? Fsum>>1 : Fsum[12:0]; 
//If bit overflow is present then increments the exponent by 1
E_Final = (Bit_Ovf==1'b1) ? E1_ST1 +1 : E1_ST1;  

//Check the normalization
//Check MSB of M_Final. if it is not 1 then perform the normalization until it comes equal to 1
while (M_Final[12] != 1  && E_Final!=0) begin  
M_Final = M_Final<<1;//Shift the bits of fraction to left by 1
E_Final = E_Final-1;//decrement the exponent by 1
end
end
always@(posedge clk_34 or rst_34) begin
  if(rst_34) begin
  Ovf_Flag_34<=1'b0;
  Unf_Flag_34<=1'b0;
  FPSUM_34 <= 16'h0000;
  end
  else begin
//check the overflow condition (2^5 -1)
if(E_Final == 31) begin                  
  Ovf_Flag_34<= 1'b1; //Raise the overflow flag
  Unf_Flag_34<=1'b0;  //Pull down the underflow flag
  FPSUM_34 <= 16'h0000; //No result
end

//Check the underflow condititon
else if (E_Final == 5'b00000) begin
  Unf_Flag_34 <=1'b1; //Raise the underflow flag
  Ovf_Flag_34 <=1'b0; //Pull down the overflow flag
  FPSUM_34 <= 16'h0000;  //No result
end

//if no overflow and underflow condition is present, then gives the final result
else  begin
  Ovf_Flag_34 <=1'b0;  //Pull down the overflow flag
  Unf_Flag_34 <= 1'b0; //Pull down the underflow flag
  FPSUM_34 <= {S_Final,E_Final,M_Final[11:2]}; //Concatinate Sign,Exponent & Mantissa
  end
end
end
endmodule

FPA_CALC_tb.v
/*This testbench is designed to test the FPCALC state code. 
-Akashay Singla*/
`timescale 1ns/1ps
module FPADD_tb();
reg clk_34, rst_34;
reg[15:0]Finput1_34,Finput2_34;
wire[15:0]FPsum_34;
wire Ovf_Flag_34,Unf_Flag_34;

fpa_adder u1(clk_34,rst_34,Finput1_34,Finput2_34,FPsum_34,Ovf_Flag_34,Unf_Flag_34);

initial begin
  $dumpfile("FPA_log.vcd");
  $dumpvars;
  #100
  $finish;
end

initial begin
  clk_34 =1'b0;
  rst_34=1'b0;
  #5
  Finput1_34 <= 16'h5620;//98
  Finput2_34 <= 16'h5948;//169
  //output 267 : 5C2C in iEE754
  #10
  Finput1_34 <= 16'h5630;//99
  Finput2_34 <= 16'hD590;//-89
  //output 10 : 4900
 #10
   Finput1_34<= 16'hD1A0; //-45
   Finput2_34<= 16'h54F0;//79
  //output 34: 5040 in iEE754
  #10
  Finput1_34 <= 16'hDC6C;//-283
  Finput2_34 <= 16'hD420;//-66
//output -349: DD74 in iEE75
 #10
  Finput1_34 <= 16'h0000; //0
  Finput2_34 <= 16'h0000;//0
//output =underflow
#10
 Finput1_34 <= 16'h0000;//0
 Finput2_34 <= 16'hD750;//-117
//output -117: D750 in IEEE654 format//

 #10
 Finput1_34 <= 16'hD6E2;//-110.125
 Finput2_34 <= 16'h563E;//99.875
 //output -10.25 : C920

 #10
 Finput1_34 <= 16'h56EE;//110.875
 Finput2_34 <= 16'h5632;//99.125
 //output underflow
//output 210: 5A90
end

always #5 clk_34 =~clk_34;
initial $monitor ("Finput1_34: %h, Finput2_34: %h, FPsum_34: %h, Ovf_Flag_34: %b, Unf_Flag_34: %b",Finput1_34, Finput2_34, FPsum_34, Ovf_Flag_34, Unf_Flag_34);
endmodule

FPA_log.vcd
$date
	Sun Feb 27 17:27:34 2022
$end

$version
	Synopsys VCS version I-2014.03-2
$end

$timescale
	1ps
$end

$comment Csum: 1 da55f05d1c91a1e1 $end


$scope module FPADD_tb $end
$var reg 1 ! clk_34 $end
$var reg 1 " rst_34 $end
$var reg 16 # Finput1_34 [15:0] $end
$var reg 16 $ Finput2_34 [15:0] $end
$var wire 1 % FPsum_34 [15] $end
$var wire 1 & FPsum_34 [14] $end
$var wire 1 ' FPsum_34 [13] $end
$var wire 1 ( FPsum_34 [12] $end
$var wire 1 ) FPsum_34 [11] $end
$var wire 1 * FPsum_34 [10] $end
$var wire 1 + FPsum_34 [9] $end
$var wire 1 , FPsum_34 [8] $end
$var wire 1 - FPsum_34 [7] $end
$var wire 1 . FPsum_34 [6] $end
$var wire 1 / FPsum_34 [5] $end
$var wire 1 0 FPsum_34 [4] $end
$var wire 1 1 FPsum_34 [3] $end
$var wire 1 2 FPsum_34 [2] $end
$var wire 1 3 FPsum_34 [1] $end
$var wire 1 4 FPsum_34 [0] $end
$var wire 1 5 Ovf_Flag_34 $end
$var wire 1 6 Unf_Flag_34 $end

$scope module u1 $end
$var wire 1 ! clk_34 $end
$var wire 1 " rst_34 $end
$var wire 16 # Finput1_34 [15:0] $end
$var wire 16 $ Finput2_34 [15:0] $end
$var reg 16 7 FPSUM_34 [15:0] $end
$var reg 1 8 Ovf_Flag_34 $end
$var reg 1 9 Unf_Flag_34 $end
$var reg 13 : M1_ST0 [12:0] $end
$var reg 13 ; M2_ST0 [12:0] $end
$var reg 13 < M1_ST1 [12:0] $end
$var reg 13 = M2_ST1 [12:0] $end
$var reg 13 > M_Final [12:0] $end
$var reg 5 ? E1_ST0 [4:0] $end
$var reg 5 @ E2_ST0 [4:0] $end
$var reg 5 A E1_ST1 [4:0] $end
$var reg 5 B E2_ST1 [4:0] $end
$var reg 5 C E_Final [4:0] $end
$var reg 1 D S1_ST0 $end
$var reg 1 E S2_ST0 $end
$var reg 1 F S1_ST1 $end
$var reg 1 G S2_ST1 $end
$var reg 1 H S_Final $end
$var reg 1 I Bit_Ovf $end
$var reg 15 J M1_Add [14:0] $end
$var reg 15 K M2_Add [14:0] $end
$var reg 15 L M_Sum [14:0] $end
$var reg 15 M Fsum [14:0] $end
$var reg 13 N M1_ST0_temp [12:0] $end
$var reg 13 O M2_ST0_temp [12:0] $end
$var reg 5 P E1_ST0_temp [4:0] $end
$var reg 5 Q E2_ST0_temp [4:0] $end
$var reg 5 R Temp [4:0] $end
$upscope $end

$upscope $end

$enddefinitions $end

#0
$dumpvars
xI
x4
x*
x)
x(
x'
x&
x%
x3
x2
x1
x0
x/
x.
x-
x,
x+
05
xD
xF
xE
xG
xH
06
0!
0"
08
09
bxxxxx ?
bxxxxx P
bxxxxx A
bxxxxx @
bxxxxx Q
bxxxxx B
bxxxxx C
bxxxxxxxxxxxxxxxx 7
bxxxxxxxxxxxxxxxx #
bxxxxxxxxxxxxxxxx $
bxxxxxxxxxxxxxxx M
bxxxxxxxxxxxxxxx J
bxxxxxxxxxxxxx :
bxxxxxxxxxxxxx N
bxxxxxxxxxxxxx <
bxxxxxxxxxxxxxxx K
bxxxxxxxxxxxxx ;
bxxxxxxxxxxxxx O
bxxxxxxxxxxxxx =
bxxxxxxxxxxxxx >
bxxxxxxxxxxxxxxx L
bxxxxx R
$end
#5000
1!
b0101011000100000 #
b0101100101001000 $
b10111 C
b1000010110000 >
1I
0H
b010000101100000 M
b010000101100000 L
b001010100100000 K
b000110001000000 J
0G
0F
b10110 A
b1010100100000 =
b0110001000000 <
b00001 R
b1010100100000 ;
b1100010000000 :
b10110 @
0E
b10101 ?
0D
#10000
0!
#15000
1!
b0101011000110000 #
b1101010110010000 $
b0101110000101100 7
0%
1&
0'
1(
1)
1*
0+
0,
0-
0.
1/
00
11
12
03
04
b10010 C
b1010000000000 >
0I
b000001010000000 M
b000001010000000 L
b110100111000000 K
b001100011000000 J
1G
b10101 A
b1011001000000 =
b1100011000000 <
b00000 R
b1011001000000 ;
b1100011000000 :
b10101 @
1E
#20000
0!
#25000
1!
b1101000110100000 #
b0101010011110000 $
b0100100100000000 7
0(
0*
1,
0/
01
02
b10100 C
b1000100000000 >
b000100010000000 M
b000100010000000 L
b001001111000000 K
b111010011000000 J
0G
1F
b1001111000000 =
b0101101000000 <
b00001 R
b1001111000000 ;
b1011010000000 :
0E
b10100 ?
1D
#30000
0!
#35000
1!
b1101110001101100 #
b1101010000100000 $
b0101000001000000 7
1(
0)
0,
1.
b10111 C
b1010111010000 >
1H
b001010111010000 M
b110101000110000 L
b111101111100000 K
b110111001010000 J
1G
b10111 A
b0010000100000 =
b1000110110000 <
b00010 R
b1000010000000 ;
b1000110110000 :
1E
b10111 ?
#40000
0!
#45000
1!
b0000000000000000 #
b0000000000000000 $
b1101110101110100 7
1%
1)
1*
1,
1/
10
12
b00000 C
b0000000000000 >
0H
b000000000000000 M
b000000000000000 L
b000000000000000 K
b000000000000000 J
0G
0F
b00000 A
b0000000000000 =
b0000000000000 <
b00000 R
b0000000000000 ;
b0000000000000 :
b00000 @
0E
b00000 ?
0D
#50000
0!
#55000
1!
b1101011101010000 $
19
16
b0000000000000000 7
0%
0&
0(
0)
0*
0,
0.
0/
00
02
b10101 C
b1110101000000 >
1H
b001110101000000 M
b110001011000000 L
b110001011000000 K
1G
b10101 A
b1110101000000 =
b10101 R
b1110101000000 ;
b10101 @
1E
#60000
0!
#65000
1!
b1101011011100010 #
b0101011000111110 $
09
06
b1101011101010000 7
1%
1&
1(
1*
1+
1,
1.
10
b10010 C
b1010010000000 >
b000001010010000 M
b111110101110000 L
b001100011111000 K
b110010001111000 J
0G
1F
b1100011111000 =
b1101110001000 <
b00000 R
b1100011111000 ;
b1101110001000 :
0E
b10101 ?
1D
#70000
0!
#75000
1!
b0101011011101110 #
b0101011000110010 $
b1100100100100000 7
0(
1)
0*
0+
0.
1/
00
b10110 C
b1101001000000 >
1I
0H
b011010010000000 M
b011010010000000 L
b001100011001000 K
b001101110111000 J
0F
b1100011001000 =
b1101110111000 <
b1100011001000 ;
b1101110111000 :
0D
#80000
0!
#85000
1!
b0101101010010000 7
0%
1(
1+
0,
1-
0/
10
